aliyun/__init__.py
aliyun/api/__init__.py
aliyun/api/base.py
aliyun/api/rest/__init__.py
hifive/__init__.py
hifive/api/__init__.py
hifive/api/base.py
hifive/api/rest/AreaEnum.py
hifive/api/rest/EducationEnum.py
hifive/api/rest/GenderEnum.py
hifive/api/rest/HFAuthorizeMusicDetailRequest.py
hifive/api/rest/HFAuthorizeMusicRequest.py
hifive/api/rest/HFBaseFavoriteRequest.py
hifive/api/rest/HFBaseHotRequest.py
hifive/api/rest/HFBaseLoginRequest.py
hifive/api/rest/HFBaseReportRequest.py
hifive/api/rest/HFBaseVisualRequest.py
hifive/api/rest/HFBaseWeatherRequest.py
hifive/api/rest/HFBitRateEnum.py
hifive/api/rest/HFBroadcastPlanRequest.py
hifive/api/rest/HFChannelRequest.py
hifive/api/rest/HFChannelSheetRequest.py
hifive/api/rest/HFClearMemberSheetMusicRequest.py
hifive/api/rest/HFClearSearchHistoryRequest.py
hifive/api/rest/HFCreateMemberSheetRequest.py
hifive/api/rest/HFDeleteMemberSheetRequest.py
hifive/api/rest/HFHQListenSliceRequest.py
hifive/api/rest/HFKHQListenRequest.py
hifive/api/rest/HFKReportListenRequest.py
hifive/api/rest/HFKTrialRequest.py
hifive/api/rest/HFMemberHQListenRequest.py
hifive/api/rest/HFMemberMusicInSheetRequest.py
hifive/api/rest/HFMemberPriceRequest.py
hifive/api/rest/HFMemberSheetMusicRequest.py
hifive/api/rest/HFMemberSubscribePayRequest.py
hifive/api/rest/HFMemberSubscribeRequest.py
hifive/api/rest/HFMemberTrialRequest.py
hifive/api/rest/HFMusicConfigRequest.py
hifive/api/rest/HFOpenMemberSheetMusicAddRequest.py
hifive/api/rest/HFOpenMemberSheetRequest.py
hifive/api/rest/HFOrderAuthorizationRequest.py
hifive/api/rest/HFOrderDetailRequest.py
hifive/api/rest/HFOrderGroupRequest.py
hifive/api/rest/HFOrderGroupSheetRequest.py
hifive/api/rest/HFOrderListenMixedRequest.py
hifive/api/rest/HFOrderListenRequest.py
hifive/api/rest/HFOrderListenSliceRequest.py
hifive/api/rest/HFOrderMusicRequest.py
hifive/api/rest/HFOrderPublishRequest.py
hifive/api/rest/HFOrderRefundRequest.py
hifive/api/rest/HFOrderSearchMusicRequest.py
hifive_openapi-4.2.1.1.dist-info/LICENSE
hifive_openapi-4.2.1.1.dist-info/METADATA
hifive_openapi-4.2.1.1.dist-info/WHEEL
hifive_openapi-4.2.1.1.dist-info/top_level.txt
hifive_openapi-4.2.1.1.dist-info/RECORD
